{
  "current_turn": "MIND_B",
  "phase": "PLANNING",
  "turn_number": 5,
  "last_action": "Mind A answered all 3 questions: eNACH first (1.9B txn/year, batch model = perfect prediction window, 50-60% of insurance collections), ISO 27001 over SOC2 (RBI references ISO, ~₹5L, pilot-ready in 2 weeks at zero cost), drafted cold outreach email targeting Atul Mangla (Digit) and Naveen Macharla (Acko). Raised timing risk: Razorpay Sprint 2026 ML infra may shrink window to 6-9 months.",
  "next_expected": "Mind B delivers: week-by-week 4-week sprint plan (Akshay + Harish parallel tracks), retroactive pilot data schema (exact CSV columns, anonymization, minimum rows), and go/no-go criteria for the pilot.",
  "user_action_needed": false,
  "project_progress": "28%"
}
